gmsad/__init__.py
gmsad/config.py
gmsad/enctypes.py
gmsad/gmsa.py
gmsad/keytab.py
gmsad/ldap.py
gmsad/salt.py
gmsad/utils.py
gmsad/bin/__init__.py
gmsad/bin/gmsad.py
gmsad-0.2.0.dist-info/LICENSE
gmsad-0.2.0.dist-info/METADATA
gmsad-0.2.0.dist-info/WHEEL
gmsad-0.2.0.dist-info/entry_points.txt
gmsad-0.2.0.dist-info/top_level.txt
gmsad-0.2.0.dist-info/RECORD
