Metadata-Version: 2.1
Name: gmsad
Version: 0.2.0
Summary: Linux service to manage gMSA accounts
Author: Vincent Ruello
Author-email: vincent.ruello@cea.fr
License-File: LICENSE
Requires-Dist: ldap3
Requires-Dist: gssapi
Requires-Dist: dnspython
Requires-Dist: pycryptodomex
Requires-Dist: asn1crypto
Provides-Extra: dev
Requires-Dist: mypy; extra == "dev"
